LICENSE
README.md
setup.py
etherscan/__init__.py
etherscan/accounts.py
etherscan/blocks.py
etherscan/client.py
etherscan/client.ropsten.py
etherscan/contracts.py
etherscan/gas_tracker.py
etherscan/logs.py
etherscan/proxies.py
etherscan/stats.py
etherscan/tokens.py
etherscan/transactions.py
etherscan_api.egg-info/PKG-INFO
etherscan_api.egg-info/SOURCES.txt
etherscan_api.egg-info/dependency_links.txt
etherscan_api.egg-info/requires.txt
etherscan_api.egg-info/top_level.txt