Metadata-Version: 2.1
Name: etherscan-api
Version: 0.1.6
Summary: Etherscan.io API wrapper
License: UNKNOWN
Platform: UNKNOWN
Classifier: Programming Language :: Python :: 3
Classifier: License :: OSI Approved :: MIT License
Classifier: Operating System :: OS Independent
License-File: LICENSE
